late/__init__.py
late/enums.py
late/ai/__init__.py
late/ai/content_generator.py
late/ai/protocols.py
late/ai/providers/__init__.py
late/ai/providers/openai.py
late/client/__init__.py
late/client/base.py
late/client/exceptions.py
late/client/late_client.py
late/client/rate_limiter.py
late/mcp/__init__.py
late/mcp/__main__.py
late/mcp/auth.py
late/mcp/config.py
late/mcp/constants.py
late/mcp/generated_tools.py
late/mcp/http_server.py
late/mcp/routes.py
late/mcp/server.py
late/mcp/tool_definitions.py
late/models/__init__.py
late/models/responses.py
late/models/_generated/__init__.py
late/models/_generated/models.py
late/pipelines/__init__.py
late/pipelines/cross_poster.py
late/pipelines/csv_scheduler.py
late/resources/__init__.py
late/resources/accounts.py
late/resources/analytics.py
late/resources/base.py
late/resources/media.py
late/resources/posts.py
late/resources/profiles.py
late/resources/queue.py
late/resources/tools.py
late/resources/users.py
late/resources/_generated/__init__.py
late/resources/_generated/account_groups.py
late/resources/_generated/accounts.py
late/resources/_generated/analytics.py
late/resources/_generated/api_keys.py
late/resources/_generated/comments.py
late/resources/_generated/connect.py
late/resources/_generated/inbox.py
late/resources/_generated/invites.py
late/resources/_generated/logs.py
late/resources/_generated/media.py
late/resources/_generated/messages.py
late/resources/_generated/posts.py
late/resources/_generated/profiles.py
late/resources/_generated/queue.py
late/resources/_generated/reddit.py
late/resources/_generated/reviews.py
late/resources/_generated/tools.py
late/resources/_generated/usage.py
late/resources/_generated/users.py
late/resources/_generated/webhooks.py
late/upload/__init__.py
late/upload/config.py
late/upload/direct.py
late/upload/protocols.py
late/upload/smart.py
late/upload/utils.py
late/upload/vercel/__init__.py
late/upload/vercel/client.py
late/upload/vercel/uploader.py
late_sdk-1.2.17.dist-info/METADATA
late_sdk-1.2.17.dist-info/WHEEL
late_sdk-1.2.17.dist-info/entry_points.txt
late_sdk-1.2.17.dist-info/licenses/LICENSE
late_sdk-1.2.17.dist-info/RECORD
