Metadata-Version: 2.4
Name: late-sdk
Version: 1.2.17
Summary: The official Python library for the Late API
Project-URL: Homepage, https://getlate.dev
Project-URL: Documentation, https://docs.getlate.dev
Project-URL: Repository, https://github.com/getlatedev/late-python
Project-URL: Issues, https://github.com/getlatedev/late-python/issues
Project-URL: Changelog, https://docs.getlate.dev/changelog
Author-email: Late <hello@getlate.dev>
License: Apache-2.0
License-File: LICENSE
Keywords: api,bluesky,facebook,instagram,late,linkedin,pinterest,reddit,scheduling,sdk,snapchat,social-media,telegram,threads,tiktok,twitter,x,youtube
Classifier: Development Status :: 4 - Beta
Classifier: Intended Audience :: Developers
Classifier: License :: OSI Approved :: Apache Software License
Classifier: Operating System :: OS Independent
Classifier: Programming Language :: Python :: 3
Classifier: Programming Language :: Python :: 3.10
Classifier: Programming Language :: Python :: 3.11
Classifier: Programming Language :: Python :: 3.12
Classifier: Programming Language :: Python :: 3.13
Classifier: Topic :: Internet :: WWW/HTTP
Classifier: Topic :: Software Development :: Libraries :: Python Modules
Classifier: Typing :: Typed
Requires-Python: >=3.10
Requires-Dist: httpx>=0.27.0
Requires-Dist: pydantic>=2.0.0
Provides-Extra: ai
Requires-Dist: openai>=1.0.0; extra == 'ai'
Provides-Extra: all
Requires-Dist: anthropic>=0.40.0; extra == 'all'
Requires-Dist: mcp>=1.0.0; extra == 'all'
Requires-Dist: openai>=1.0.0; extra == 'all'
Provides-Extra: anthropic
Requires-Dist: anthropic>=0.40.0; extra == 'anthropic'
Provides-Extra: dev
Requires-Dist: datamodel-code-generator>=0.26.0; extra == 'dev'
Requires-Dist: mypy>=1.13.0; extra == 'dev'
Requires-Dist: pytest-asyncio>=0.24.0; extra == 'dev'
Requires-Dist: pytest-cov>=6.0.0; extra == 'dev'
Requires-Dist: pytest>=8.0.0; extra == 'dev'
Requires-Dist: pyyaml>=6.0.0; extra == 'dev'
Requires-Dist: respx>=0.21.0; extra == 'dev'
Requires-Dist: ruff>=0.8.0; extra == 'dev'
Provides-Extra: mcp
Requires-Dist: mcp>=1.0.0; extra == 'mcp'
Requires-Dist: starlette>=0.42.0; extra == 'mcp'
Requires-Dist: uvicorn[standard]>=0.32.0; extra == 'mcp'
